graynet/__init__.py
graynet/__main__.py
graynet/_version.py
graynet/config_graynet.py
graynet/freesurfer.py
graynet/multi_edge.py
graynet/parcellate.py
graynet/run_workflow.py
graynet/utils.py
graynet/vis_network.py
graynet/volumetric.py
graynet/atlases/cat_aal/aal.csv
graynet/atlases/cat_aal/aal.nii
graynet/atlases/cat_aal/aal.txt
graynet/atlases/cat_aal/atlas.nii
graynet/atlases/cat_aal/brainmask.nii
graynet/atlases/cat_ibsr/atlas.nii
graynet/atlases/cat_ibsr/brainmask.nii
graynet/atlases/cat_ibsr/ibsr.csv
graynet/atlases/cat_ibsr/ibsr.nii
graynet/atlases/cat_ibsr/ibsr.txt
graynet/atlases/cat_lpba40/atlas.nii
graynet/atlases/cat_lpba40/brainmask.nii
graynet/atlases/cat_lpba40/lpba40.csv
graynet/atlases/cat_lpba40/lpba40.nii
graynet/atlases/cat_lpba40/lpba40.txt
graynet/atlases/fsaverage/label/lh.aparc.annot
graynet/atlases/fsaverage/label/rh.aparc.annot
graynet/atlases/fsaverage/surf/lh.orig
graynet/atlases/fsaverage/surf/rh.orig
graynet/atlases/glasser2016/fsaverage_annot_figshare3498446/label/lh.HCP-MMP1.annot
graynet/atlases/glasser2016/fsaverage_annot_figshare3498446/label/lh.aparc.annot
graynet/atlases/glasser2016/fsaverage_annot_figshare3498446/label/rh.HCP-MMP1.annot
graynet/atlases/glasser2016/fsaverage_annot_figshare3498446/label/rh.aparc.annot
graynet/atlases/vbm_CAT12/brainmask.nii
graynet/atlases/yeo2011_fsaverage5/Yeo_JNeurophysiol11_FreeSurfer_README
graynet/atlases/yeo2011_fsaverage5/label/lh.aparc.annot
graynet/atlases/yeo2011_fsaverage5/label/rh.aparc.annot
graynet/atlases/yeo2011_fsaverage5/surf/lh.orig
graynet/atlases/yeo2011_fsaverage5/surf/rh.orig
graynet/atlases/yeo2011_fsaverage6/Yeo_JNeurophysiol11_FreeSurfer_README
graynet/atlases/yeo2011_fsaverage6/label/lh.aparc.annot
graynet/atlases/yeo2011_fsaverage6/label/rh.aparc.annot
graynet/atlases/yeo2011_fsaverage6/surf/lh.orig
graynet/atlases/yeo2011_fsaverage6/surf/rh.orig
graynet/atlases/yeo2011_fsaverage_highres/Yeo_JNeurophysiol11_FreeSurfer_README
graynet-0.5.7.dist-info/METADATA
graynet-0.5.7.dist-info/WHEEL
graynet-0.5.7.dist-info/entry_points.txt
graynet-0.5.7.dist-info/licenses/LICENSE
graynet-0.5.7.dist-info/RECORD
