Metadata-Version: 2.4
Name: graynet
Version: 0.5.7
Summary: Individualized single-subject networks from T1 mri features such as cortical thickness and gray matter density. 
Project-URL: Homepage, https://github.com/raamana/graynet
Author-email: Pradeep Reddy Raamana <raamana@gmail.com>
License-Expression: MIT
License-File: LICENSE
Classifier: Intended Audience :: Science/Research
Classifier: License :: OSI Approved :: MIT License
Classifier: Operating System :: MacOS
Classifier: Operating System :: Microsoft :: Windows
Classifier: Operating System :: POSIX
Classifier: Operating System :: Unix
Classifier: Programming Language :: Python
Classifier: Programming Language :: Python :: 3.6
Classifier: Topic :: Scientific/Engineering
Classifier: Topic :: Software Development
Requires-Dist: hiwenet
Requires-Dist: medpy
Requires-Dist: networkx
Requires-Dist: nibabel
Requires-Dist: numpy
Requires-Dist: pyradigm
Requires-Dist: scipy
